texsnip/__init__.py
texsnip/texsnip.py
texsnip-1.1.0.dist-info/LICENSE
texsnip-1.1.0.dist-info/METADATA
texsnip-1.1.0.dist-info/WHEEL
texsnip-1.1.0.dist-info/top_level.txt
texsnip-1.1.0.dist-info/RECORD
