Metadata-Version: 2.1
Name: texsnip
Version: 1.1.0
Summary: Tiny package to quickly add LaTeX text to your favorite vector graphics package.
Home-page: https://github.com/pgrit/texsnip
Author: Pascal Grittmann
Author-email: grittmann@cg.uni-saarland.de
Classifier: Programming Language :: Python :: 3
Classifier: License :: OSI Approved :: MIT License
Classifier: Operating System :: OS Independent
Requires-Python: >=3.6
License-File: LICENSE
